Workbook

Sheet Mapping
A1: Bamboo id | B1: salus id | C1: Name
A2: =bambooTrainingTypes!A2 -> 1154 | B2: =_xlfn.XLOOKUP(_xlfn.XLOOKUP(Mapping!A2,bambooTrainingTypes!A:A,bambooTrainingTypes!B:B),salusCertTypes!B:B,salusCertTypes!A:A) -> #N/A | C2: =_xlfn.XLOOKUP(Mapping!B2,salusCertTypes!A:A,salusCertTypes!B:B) -> #N/A
A3: =bambooTrainingTypes!A3 -> 1156 | B3: =_xlfn.XLOOKUP(_xlfn.XLOOKUP(Mapping!A3,bambooTrainingTypes!A:A,bambooTrainingTypes!B:B),salusCertTypes!B:B,salusCertTypes!A:A) -> 39453 | C3: =_xlfn.XLOOKUP(Mapping!B3,salusCertTypes!A:A,salusCertTypes!B:B) -> CPR/AED & First Aid
A4: =bambooTrainingTypes!A4 -> 1159 | B4: =_xlfn.XLOOKUP(_xlfn.XLOOKUP(Mapping!A4,bambooTrainingTypes!A:A,bambooTrainingTypes!B:B),salusCertTypes!B:B,salusCertTypes!A:A) -> 39471 | C4: =_xlfn.XLOOKUP(Mapping!B4,salusCertTypes!A:A,salusCertTypes!B:B) -> Roadway Worker Protection (RWP / Railroad)
A5: =bambooTrainingTypes!A5 -> 1209 | B5: =_xlfn.XLOOKUP(_xlfn.XLOOKUP(Mapping!A5,bambooTrainingTypes!A:A,bambooTrainingTypes!B:B),salusCertTypes!B:B,salusCertTypes!A:A) -> 39454 | C5: =_xlfn.XLOOKUP(Mapping!B5,salusCertTypes!A:A,salusCertTypes!B:B) -> Crisis Management
A6: =bambooTrainingTypes!A6 -> 1210 | B6: =_xlfn.XLOOKUP(_xlfn.XLOOKUP(Mapping!A6,bambooTrainingTypes!A:A,bambooTrainingTypes!B:B),salusCertTypes!B:B,salusCertTypes!A:A) -> 39483 | C6: =_xlfn.XLOOKUP(Mapping!B6,salusCertTypes!A:A,salusCertTypes!B:B) -> Job Hazard Analysis
A7: =bambooTrainingTypes!A7 -> 1211 | B7: =_xlfn.XLOOKUP(_xlfn.XLOOKUP(Mapping!A7,bambooTrainingTypes!A:A,bambooTrainingTypes!B:B),salusCertTypes!B:B,salusCertTypes!A:A) -> #N/A | C7: =_xlfn.XLOOKUP(Mapping!B7,salusCertTypes!A:A,salusCertTypes!B:B) -> #N/A
A8: =bambooTrainingTypes!A8 -> 1232 | B8: =_xlfn.XLOOKUP(_xlfn.XLOOKUP(Mapping!A8,bambooTrainingTypes!A:A,bambooTrainingTypes!B:B),salusCertTypes!B:B,salusCertTypes!A:A) -> #N/A | C8: =_xlfn.XLOOKUP(Mapping!B8,salusCertTypes!A:A,salusCertTypes!B:B) -> #N/A
A9: =bambooTrainingTypes!A9 -> 1233 | B9: =_xlfn.XLOOKUP(_xlfn.XLOOKUP(Mapping!A9,bambooTrainingTypes!A:A,bambooTrainingTypes!B:B),salusCertTypes!B:B,salusCertTypes!A:A) -> 39463 | C9: =_xlfn.XLOOKUP(Mapping!B9,salusCertTypes!A:A,salusCertTypes!B:B) -> Aerial Lifts Operator Certification
A10: =bambooTrainingTypes!A10 -> 1236 | B10: =_xlfn.XLOOKUP(_xlfn.XLOOKUP(Mapping!A10,bambooTrainingTypes!A:A,bambooTrainingTypes!B:B),salusCertTypes!B:B,salusCertTypes!A:A) -> #N/A | C10: =_xlfn.XLOOKUP(Mapping!B10,salusCertTypes!A:A,salusCertTypes!B:B) -> #N/A
A11: =bambooTrainingTypes!A11 -> 1237 | B11: =_xlfn.XLOOKUP(_xlfn.XLOOKUP(Mapping!A11,bambooTrainingTypes!A:A,bambooTrainingTypes!B:B),salusCertTypes!B:B,salusCertTypes!A:A) -> 39458 | C11: =_xlfn.XLOOKUP(Mapping!B11,salusCertTypes!A:A,salusCertTypes!B:B) -> Forklift Operator Certification
A12: =bambooTrainingTypes!A12 -> 1238 | B12: =_xlfn.XLOOKUP(_xlfn.XLOOKUP(Mapping!A12,bambooTrainingTypes!A:A,bambooTrainingTypes!B:B),salusCertTypes!B:B,salusCertTypes!A:A) -> #N/A | C12: =_xlfn.XLOOKUP(Mapping!B12,salusCertTypes!A:A,salusCertTypes!B:B) -> #N/A
A13: =bambooTrainingTypes!A13 -> 1240 | B13: =_xlfn.XLOOKUP(_xlfn.XLOOKUP(Mapping!A13,bambooTrainingTypes!A:A,bambooTrainingTypes!B:B),salusCertTypes!B:B,salusCertTypes!A:A) -> #N/A | C13: =_xlfn.XLOOKUP(Mapping!B13,salusCertTypes!A:A,salusCertTypes!B:B) -> #N/A
... A1635: =bambooTrainingTypes!A1635 -> 4417 | B1635: =_xlfn.XLOOKUP(_xlfn.XLOOKUP(Mapping!A1635,bambooTrainingTypes!A:A,bambooTrainingTypes!B:B),salusCertTypes!B:B,salusCertTypes!A:A) -> #N/A | C1635: =_xlfn.XLOOKUP(Mapping!B1635,salusCertTypes!A:A,salusCertTypes!B:B) -> #N/A

Sheet bambooTrainingTypes
A1: id | B1: name | C1: renewable | D1: frequency | E1: required | F1: categoryId | G1: categoryName | H1: dueFromHireDate | I1: allowEmployeesToMarkComplete | J1: linkUrl | K1: description
A2: 1154 | B2: Inactive: 10 Hour OSHA (retired version) | C2: FALSE | D2: 0 | E2: FALSE | F2: 19864 | G2: Safety | I2: FALSE | J2: https://stacywitbeck.myabsorb.com/admin/oauth/bamboohrssoauthentication?id=770d7f65-0291-4948-95ce-b831ca4e1236&courseId=4159c290-c715-4305-ae17-25ea0ca2f8a1 | K2: Online Course: OSHA 10-Hour Construction
A3: 1156 | B3: CPR/AED & First Aid | C3: TRUE | D3: 24 | E3: TRUE | F3: 19864 | G3: Safety | I3: FALSE
A4: 1159 | B4: Roadway Worker Protection (RWP / Railroad) | C4: TRUE | D4: 12 | E4: TRUE | F4: 19864 | G4: Safety | H4: 1 day | I4: FALSE
A5: 1209 | B5: Crisis Management | C5: FALSE | D5: 0 | E5: TRUE | F5: 19864 | G5: Safety | I5: FALSE
A6: 1210 | B6: Job Hazard Analysis | C6: FALSE | D6: 0 | E6: TRUE | F6: 19864 | G6: Safety | I6: FALSE
A7: 1211 | B7: Supervisor Drug and Alcohol Awareness (Reasonable Suspicion) | C7: FALSE | D7: 0 | E7: FALSE | F7: 19864 | G7: Safety | I7: FALSE | J7: https://stacywitbeck.myabsorb.com/admin/oauth/bamboohrssoauthentication?id=770d7f65-0291-4948-95ce-b831ca4e1236&courseId=9b9b083c-3658-4959-8de4-55157a7cee2c | K7: Online Course:
A8: 1232 | B8: Inactive: 8 Hour HAZWOPER Refresher (2022 Retired Version) | C8: FALSE | D8: 0 | E8: FALSE | F8: 19864 | G8: Safety | I8: FALSE | J8: https://stacywitbeck.myabsorb.com/admin/oauth/bamboohrssoauthentication?id=770d7f65-0291-4948-95ce-b831ca4e1236&courseId=f5030fb5-3270-4d75-a8dd-6f13066591ef | K8: Online Course: HAZWOPER 2019 Refresher (8-Hour)
A9: 1233 | B9: Aerial Lifts Operator Certification | C9: TRUE | D9: 36 | E9: FALSE | F9: 19864 | G9: Safety | I9: FALSE
A10: 1236 | B10: Flagger Certification or Training | C10: TRUE | D10: 36 | E10: FALSE | F10: 19864 | G10: Safety | I10: FALSE
A11: 1237 | B11: Forklift Operator Certification | C11: TRUE | D11: 36 | E11: FALSE | F11: 19864 | G11: Safety | I11: FALSE
A12: 1238 | B12: Respiratory Protection - Users | C12: TRUE | D12: 12 | E12: FALSE | F12: 19864 | G12: Safety | I12: FALSE
A13: 1240 | B13: Traffic Control Supervisor/Manager Certification | C13: TRUE | D13: 36 | E13: FALSE | F13: 19864 | G13: Safety | I13: FALSE
A14: 1241 | B14: Lead Awareness | C14: TRUE | D14: 12 | E14: FALSE | F14: 19864 | G14: Safety | I14: FALSE
A15: 1280 | B15: Heat Illness Prevention - Employees | C15: TRUE | D15: 12 | E15: FALSE | F15: 19864 | G15: Safety | I15: FALSE | J15: https://stacywitbeck.myabsorb.com/admin/oauth/bamboohrssoauthentication?id=770d7f65-0291-4948-95ce-b831ca4e1236&courseId=12679408-792d-4109-9114-0918538666c9 | K15: Online Course: Heat Stress / Heat Illness for Construction
A16: 1281 | B16: Heat Illness Prevention - Supervisors | C16: TRUE | D16: 12 | E16: FALSE | F16: 19864 | G16: Safety | I16: FALSE
A17: 1350 | B17: Traffic Control Maintainer Certification | C17: TRUE | D17: 36 | E17: FALSE | F17: 19864 | G17: Safety | I17: FALSE
A18: 1616 | B18: On Track Safety (Light Rail) | C18: TRUE | D18: 12 | E18: TRUE | F18: 19864 | G18: Safety | I18: FALSE
A19: 1617 | B19: Railroad Contractor Orientation | C19: TRUE | D19: 12 | E19: FALSE | F19: 19864 | G19: Safety | I19: FALSE
A20: 1619 | B20: Roadway Maintenance Machine Operator (RMM / Railroad) | C20: TRUE | D20: 12 | E20: FALSE | F20: 19864 | G20: Safety | I20: FALSE
A21: 1803 | B21: Crane Operator Certification (CCO) | C21: TRUE | D21: 60 | E21: FALSE | F21: 19864 | G21: Safety | I21: FALSE
A22: 1804 | B22: Supervisor Safety Orientation | C22: FALSE | D22: 0 | E22: TRUE | F22: 19864 | G22: Safety | H22: 1 day | I22: FALSE
A23: 1845 | B23: Power Tool Topic 01 - Chain Saws | C23: FALSE | D23: 0 | E23: FALSE | F23: 19864 | G23: Safety | I23: FALSE
A24: 1846 | B24: Power Tool Topic 02 - Cut-Off Saws | C24: FALSE | D24: 0 | E24: FALSE | F24: 19864 | G24: Safety | I24: FALSE
A25: 1847 | B25: Power Tool Topic 03 - Corded Saws | C25: FALSE | D25: 0 | E25: FALSE | F25: 19864 | G25: Safety | I25: FALSE
A26: 1848 | B26: Power Tool Topic 04 - Circular Saws | C26: FALSE | D26: 0 | E26: FALSE | F26: 19864 | G26: Safety | I26: FALSE
A27: 1850 | B27: Power Tool Topic 06 - Grinders | C27: FALSE | D27: 0 | E27: FALSE | F27: 19864 | G27: Safety | I27: FALSE
A28: 1851 | B28: Power Tool Topic 07 - Corded Drills | C28: FALSE | D28: 0 | E28: FALSE | F28: 19864 | G28: Safety | I28: FALSE
A29: 1852 | B29: Power Tool Topic 08 - Percussion Tools | C29: FALSE | D29: 0 | E29: FALSE | F29: 19864 | G29: Safety | I29: FALSE
A30: 1853 | B30: Power Tool Topic 09 - Generators | C30: FALSE | D30: 0 | E30: FALSE | F30: 19864 | G30: Safety | I30: FALSE
A31: 1854 | B31: Power Tool Topic 10 - Pneumatic (Air) Tools | C31: FALSE | D31: 0 | E31: FALSE | F31: 19864 | G31: Safety | I31: FALSE
A32: 1855 | B32: Power Tool Topic 11 - Nail Guns | C32: FALSE | D32: 0 | E32: FALSE | F32: 19864 | G32: Safety | I32: FALSE
A33: 1858 | B33: Power Tool Topic 14 - Cordless Tools | C33: FALSE | D33: 0 | E33: FALSE | F33: 19864 | G33: Safety | I33: FALSE
A34: 1859 | B34: Power Tool Topic 15 - Vibratory Rammers (Jumping Jacks) | C34: FALSE | D34: 0 | E34: FALSE | F34: 19864 | G34: Safety | I34: FALSE
... A37: 1865 | B37: Qualified Signal Person | C37: FALSE | D37: 0 | E37: FALSE | F37: 19864 | G37: Safety | I37: FALSE
A38: 1866 | B38: Inactive: 30 Hour OSHA (retired version) | C38: FALSE | D38: 0 | E38: FALSE | F38: 19864 | G38: Safety | I38: FALSE | J38: https://stacywitbeck.myabsorb.com/admin/oauth/bamboohrssoauthentication?id=770d7f65-0291-4948-95ce-b831ca4e1236&courseId=eff1871b-421d-41cc-881b-e88ebb2791d3 | K38: Online Course: OSHA 30-Hour Construction
A39: 1867 | B39: 40 Hour HAZWOPER | C39: FALSE | D39: 0 | E39: FALSE | F39: 19864 | G39: Safety | I39: FALSE | J39: https://stacywitbeck.myabsorb.com/admin/oauth/bamboohrssoauthentication?id=770d7f65-0291-4948-95ce-b831ca4e1236&courseId=d265d6bf-3cdd-4a3d-abd4-00006a800606 | K39: Online Course: HAZWOPER 40-Hour for All Industries
A40: 1868 | B40: Incident Investigation | C40: FALSE | D40: 0 | E40: FALSE | F40: 19864 | G40: Safety | I40: FALSE
A41: 1869 | B41: Confined Space Atmospheric Testing (Gas Detectors) | C41: FALSE | D41: 0 | E41: FALSE | F41: 19864 | G41: Safety | I41: FALSE
A42: 1870 | B42: Inactive: Bloodborne Pathogens (Click Safety) | C42: FALSE | D42: 0 | E42: FALSE | F42: 19864 | G42: Safety | I42: FALSE | J42: https://stacywitbeck.myabsorb.com/admin/oauth/bamboohrssoauthentication?id=770d7f65-0291-4948-95ce-b831ca4e1236&courseId=1ed12e63-92da-4278-abd3-5badb52cbebf | K42: Online Course: Bloodborne Pathogens for Construction
A43: 1871 | B43: Confined Space Competent Person | C43: FALSE | D43: 0 | E43: FALSE | F43: 19864 | G43: Safety | I43: FALSE
A44: 1872 | B44: Excavations/Trenches Competent Person | C44: FALSE | D44: 0 | E44: FALSE | F44: 19864 | G44: Safety | I44: FALSE | J44: https://stacywitbeck.myabsorb.com/admin/oauth/bamboohrssoauthentication?id=770d7f65-0291-4948-95ce-b831ca4e1236&courseId=42c8d520-3261-4bd3-8e67-785d80eb162a | K44: Online Course: Competent Person, Excavations for Construction
A45: 1873 | B45: Fall Protection Competent Person | C45: FALSE | D45: 0 | E45: FALSE | F45: 19864 | G45: Safety | I45: FALSE | J45: https://stacywitbeck.myabsorb.com/admin/oauth/bamboohrssoauthentication?id=770d7f65-0291-4948-95ce-b831ca4e1236&courseId=c1aba23c-f4f9-48c1-95af-795850f015e2 | K45: Online Course: Competent Person, Fall Protection for Construction (UPDATED)
A46: 1874 | B46: Scaffolding Competent Person | C46: FALSE | D46: 0 | E46: FALSE | F46: 19864 | G46: Safety | I46: FALSE
A47: 1875 | B47: Confined Space Entry | C47: FALSE | D47: 0 | E47: FALSE | F47: 19864 | G47: Safety | I47: FALSE
A48: 1876 | B48: Defensive Driving | C48: FALSE | D48: 0 | E48: FALSE | F48: 19864 | G48: Safety | I48: FALSE
A49: 1877 | B49: Electrical Safety | C49: FALSE | D49: 0 | E49: FALSE | F49: 19864 | G49: Safety | I49: FALSE
A50: 1878 | B50: Shift Prep and Stretch Breaks Coach | C50: FALSE | D50: 0 | E50: FALSE | F50: 19864 | G50: Safety | I50: FALSE
A51: 1879 | B51: Inactive: Excavations/Trenches Safety (Inactive) | C51: FALSE | D51: 0 | E51: FALSE | F51: 19864 | G51: Safety | I51: FALSE | J51: https://stacywitbeck.myabsorb.com/admin/oauth/bamboohrssoauthentication?id=770d7f65-0291-4948-95ce-b831ca4e1236&courseId=b3e0c818-b0c4-4070-832e-1685dcf4a158 | K51: Online Course: Excavation Safety for Construction
A52: 1880 | B52: Fall Protection Safety | C52: FALSE | D52: 0 | E52: FALSE | F52: 19864 | G52: Safety | I52: FALSE | J52: https://stacywitbeck.myabsorb.com/admin/oauth/bamboohrssoauthentication?id=770d7f65-0291-4948-95ce-b831ca4e1236&courseId=25ba0ef0-85db-4c5f-a692-0a9240023fc4 | K52: Online Course: Fall Protection for Construction
A53: 1881 | B53: Hoisting & Lifting - Non-Critical Lifts | C53: FALSE | D53: 0 | E53: FALSE | F53: 19864 | G53: Safety | I53: FALSE
A54: 1882 | B54: Laser Qualified Operator | C54: FALSE | D54: 0 | E54: FALSE | F54: 19864 | G54: Safety | I54: FALSE
A55: 1883 | B55: Overhead Utility Safety | C55: FALSE | D55: 0 | E55: FALSE | F55: 19864 | G55: Safety | I55: FALSE
A56: 1884 | B56: Powder Actuated Tools Qualified Operator | C56: FALSE | D56: 0 | E56: FALSE | F56: 19864 | G56: Safety | I56: FALSE
A57: 1885 | B57: Professional Trench Rescue Awareness | C57: FALSE | D57: 0 | E57: FALSE | F57: 19864 | G57: Safety | I57: FALSE
A58: 1886 | B58: Rigging Fundamentals | C58: FALSE | D58: 0 | E58: FALSE | F58: 19864 | G58: Safety | I58: FALSE
A59: 1887 | B59: Scaffolds User | C59: FALSE | D59: 0 | E59: FALSE | F59: 19864 | G59: Safety | I59: FALSE
A60: 1888 | B60: Silica Awareness | C60: FALSE | D60: 0 | E60: FALSE | F60: 19864 | G60: Safety | I60: FALSE | J60: https://stacywitbeck.myabsorb.com/admin/oauth/bamboohrssoauthentication?id=770d7f65-0291-4948-95ce-b831ca4e1236&courseId=b1d1ca0c-168d-445c-b380-c46380238cf7 | K60: Online Course: Respirable Crystalline Silica Awareness for Construction
A61: 1889 | B61: Underground Utility / Potholing Safety | C61: FALSE | D61: 0 | E61: FALSE | F61: 19864 | G61: Safety | I61: FALSE
A62: 1890 | B62: On Track Safety (Amtrak) | C62: TRUE | D62: 12 | E62: TRUE | F62: 19864 | G62: Safety | I62: FALSE
A63: 1891 | B63: Heavy Equipment: Backhoe Loader | C63: FALSE | D63: 0 | E63: FALSE | F63: 19864 | G63: Safety | I63: FALSE
A64: 1892 | B64: Heavy Equipment: Concrete Paving Machine | C64: FALSE | D64: 0 | E64: FALSE | F64: 19864 | G64: Safety | I64: FALSE
A65: 1893 | B65: Heavy Equipment: Dozer | C65: FALSE | D65: 0 | E65: FALSE | F65: 19864 | G65: Safety | I65: FALSE
A66: 1894 | B66: Heavy Equipment: Excavator (Hydraulic & Compact) | C66: FALSE | D66: 0 | E66: FALSE | F66: 19864 | G66: Safety | I66: FALSE
A67: 1895 | B67: Heavy Equipment: Fuel/Lube Truck | C67: FALSE | D67: 0 | E67: FALSE | F67: 19864 | G67: Safety | I67: FALSE
A68: 1896 | B68: Heavy Equipment: Mechanic Truck | C68: FALSE | D68: 0 | E68: FALSE | F68: 19864 | G68: Safety | I68: FALSE
A69: 1897 | B69: Heavy Equipment: Motor Grader | C69: FALSE | D69: 0 | E69: FALSE | F69: 19864 | G69: Safety | I69: FALSE
A70: 1898 | B70: Heavy Equipment: Roller (Single & Double Drum) | C70: FALSE | D70: 0 | E70: FALSE | F70: 19864 | G70: Safety | I70: FALSE
A71: 1899 | B71: Heavy Equipment: Scraper | C71: FALSE | D71: 0 | E71: FALSE | F71: 19864 | G71: Safety | I71: FALSE
A72: 1900 | B72: Heavy Equipment: Skid-Steer Loader | C72: FALSE | D72: 0 | E72: FALSE | F72: 19864 | G72: Safety | I72: FALSE
... A92: 1920 | B92: Rail Equipment: Tie Spacer | C92: FALSE | D92: 0 | E92: FALSE | F92: 19864 | G92: Safety | I92: FALSE
A93: 1921 | B93: Equipment Safety Training Program | C93: FALSE | D93: 0 | E93: TRUE | F93: 19864 | G93: Safety | H93: 1 day | I93: FALSE
A94: 1922 | B94: e-RAILSAFE | C94: TRUE | D94: 24 | E94: TRUE | F94: 19864 | G94: Safety | I94: FALSE
A95: 1923 | B95: AGC STP Unit 7 - Accident Prevention & Loss Control | C95: FALSE | D95: 0 | E95: FALSE | F95: 19864 | G95: Safety | I95: FALSE
A96: 1924 | B96: Fire Watch | C96: FALSE | D96: 0 | E96: FALSE | F96: 19864 | G96: Safety | I96: FALSE
A97: 1925 | B97: Process Safety Management | C97: TRUE | D97: 12 | E97: FALSE | F97: 19864 | G97: Safety | I97: FALSE
A98: 1926 | B98: CARB Regulations | C98: FALSE | D98: 0 | E98: FALSE | F98: 19118 | G98: Equipment | I98: FALSE
A99: 1927 | B99: ACEM Spring Meeting | C99: FALSE | D99: 0 | E99: FALSE | F99: 19109 | G99: Industry/Professional Conferences | I99: FALSE
A100: 1928 | B100: AGC Leadership in Construction | C100: FALSE | D100: 0 | E100: FALSE | F100: 19112 | G100: Leadership/Management | I100: FALSE
A101: 1929 | B101: AGC PM Course | C101: FALSE | D101: 0 | E101: FALSE | F101: 19112 | G101: Leadership/Management | I101: FALSE
A102: 1931 | B102: AGC Utah Convention | C102: FALSE | D102: 0 | E102: FALSE | F102: 19109 | G102: Industry/Professional Conferences | I102: FALSE
A103: 1932 | B103: Agtek Webinar | C103: FALSE | D103: 0 | E103: FALSE | F103: 19115 | G103: Estimating/Scheduling | I103: FALSE
A104: 1933 | B104: AGTEK (3 hrs) | C104: FALSE | D104: 0 | E104: FALSE | F104: 19115 | G104: Estimating/Scheduling | I104: FALSE
A105: 1934 | B105: Agtek (8hrs) | C105: FALSE | D105: 0 | E105: FALSE | F105: 19115 | G105: Estimating/Scheduling | I105: FALSE
... A111: 1940 | B111: Asphalt Density Testing (6 hrs) | C111: FALSE | D111: 0 | E111: FALSE | F111: 19117 | G111: Quality | I111: FALSE
A112: 1941 | B112: Benefits of Lean/Integrated Project Delivery to Owners | C112: FALSE | D112: 0 | E112: FALSE | I112: FALSE
A113: 1942 | B113: Utility Locates Training | C113: FALSE | D113: 0 | E113: FALSE | F113: 19864 | G113: Safety | I113: FALSE
A114: 1943 | B114: Brown Bag - Czech Special Track | C114: FALSE | D114: 0 | E114: FALSE | F114: 19247 | G114: Track | I114: FALSE
A115: 1944 | B115: Brown Bag - Excel Tips & Tricks | C115: FALSE | D115: 0 | E115: FALSE | F115: 19113 | G115: Administrative/Document Control | I115: FALSE
A116: 1945 | B116: Brown Bag - Insurance | C116: FALSE | D116: 0 | E116: FALSE | F116: 19120 | G116: Insurance/Claims/Contracts | I116: FALSE
A117: 1946 | B117: Brown Bag - JHA | C117: FALSE | D117: 0 | E117: FALSE | F117: 19864 | G117: Safety | I117: FALSE
A118: 1947 | B118: Brown Bag - Project Controls | C118: FALSE | D118: 0 | E118: FALSE | F118: 19111 | G118: Brown Bag | I118: FALSE
A119: 1948 | B119: Brown Bag - QA/QC Training with CM | C119: FALSE | D119: 0 | E119: FALSE | F119: 19117 | G119: Quality | I119: FALSE
A120: 1949 | B120: Brown Bag - Schedule Development | C120: FALSE | D120: 0 | E120: FALSE | F120: 19115 | G120: Estimating/Scheduling | I120: FALSE
A121: 1950 | B121: Brown Bag - Schedule Overview | C121: FALSE | D121: 0 | E121: FALSE | F121: 19115 | G121: Estimating/Scheduling | I121: FALSE
A122: 1951 | B122: Brown Bag - Subcontract Management | C122: FALSE | D122: 0 | E122: FALSE | F122: 19111 | G122: Brown Bag | I122: FALSE
A123: 1952 | B123: Certified Labs Lubrication | C123: FALSE | D123: 0 | E123: FALSE | I123: FALSE
A124: 1953 | B124: Claims Documentation - United Contractors (EUCA) | C124: FALSE | D124: 0 | E124: FALSE | F124: 19120 | G124: Insurance/Claims/Contracts | I124: FALSE
A125: 1955 | B125: Conference for Women | C125: FALSE | D125: 0 | E125: FALSE | F125: 19109 | G125: Industry/Professional Conferences | I125: FALSE
A126: 1956 | B126: Construction Contracts Seminar | C126: FALSE | D126: 0 | E126: FALSE | F126: 19120 | G126: Insurance/Claims/Contracts | I126: FALSE
...

Sheet salusCertTypes
A1: id | B1: name | C1: required | D1: slug | E1: companyId
A2: 39453 | B2: CPR/AED & First Aid | C2: FALSE | D2: cpraed--first-aid | E2: 1246989 | F2: {=_xlfn.XLOOKUP(salusCertTypes!A2,Table1[[#All],[salus id]],Table1[[#All],[Name]])} -> CPR/AED & First Aid
A3: 39454 | B3: Crisis Management | C3: FALSE | D3: crisis-management | E3: 1246989 | F3: {=_xlfn.XLOOKUP(salusCertTypes!A3,Table1[[#All],[salus id]],Table1[[#All],[Name]])} -> Crisis Management
A4: 39456 | B4: 10 Hour OSHA | C4: FALSE | D4: 10-hour-osha | E4: 1246989 | F4: {=_xlfn.XLOOKUP(salusCertTypes!A4,Table1[[#All],[salus id]],Table1[[#All],[Name]])} -> 10 Hour OSHA
A5: 39457 | B5: Supervisor Safety Orientation | C5: FALSE | D5: supervisor-safety-orientation | E5: 1246989 | F5: {=_xlfn.XLOOKUP(salusCertTypes!A5,Table1[[#All],[salus id]],Table1[[#All],[Name]])} -> Supervisor Safety Orientation
A6: 39458 | B6: Forklift Operator Certification | C6: FALSE | D6: forklift-operator-certification | E6: 1246989 | F6: {=_xlfn.XLOOKUP(salusCertTypes!A6,Table1[[#All],[salus id]],Table1[[#All],[Name]])} -> Forklift Operator Certification
A7: 39459 | B7: Supervisor Drug and Alcohol Awareness (Reasonable Suspicion) Non-DOT | C7: FALSE | D7: supervisor-drug-and-alcohol-awareness-reasonable-suspicion-non-dot | E7: 1246989 | F7: {=_xlfn.XLOOKUP(salusCertTypes!A7,Table1[[#All],[salus id]],Table1[[#All],[Name]])} -> Supervisor Drug and Alcohol Awareness (Reasonable Suspicion) Non-DOT
A8: 39460 | B8: Safety Culture Excellence Workshop (SCEW) | C8: FALSE | D8: safety-culture-excellence-workshop-scew | E8: 1246989 | F8: {=_xlfn.XLOOKUP(salusCertTypes!A8,Table1[[#All],[salus id]],Table1[[#All],[Name]])} -> Safety Culture Excellence Workshop (SCEW)
A9: 39461 | B9: Risk Tolerance and Hazard Recognition | C9: FALSE | D9: risk-tolerance-and-hazard-recognition | E9: 1246989 | F9: {=_xlfn.XLOOKUP(salusCertTypes!A9,Table1[[#All],[salus id]],Table1[[#All],[Name]])} -> Risk Tolerance and Hazard Recognition
A10: 39462 | B10: STCKY Training (Sh!t That Can Kill You) | C10: FALSE | D10: stcky-training-sht-that-can-kill-you | E10: 1246989 | F10: {=_xlfn.XLOOKUP(salusCertTypes!A10,Table1[[#All],[salus id]],Table1[[#All],[Name]])} -> STCKY Training (Sh!t That Can Kill You)
A11: 39463 | B11: Aerial Lifts Operator Certification | C11: FALSE | D11: aerial-lifts-operator-certification | E11: 1246989 | F11: {=_xlfn.XLOOKUP(salusCertTypes!A11,Table1[[#All],[salus id]],Table1[[#All],[Name]])} -> Aerial Lifts Operator Certification
A12: 39464 | B12: Heat Illness Prevention - Supervisors | C12: FALSE | D12: heat-illness-prevention---supervisors | E12: 1246989 | F12: {=_xlfn.XLOOKUP(salusCertTypes!A12,Table1[[#All],[salus id]],Table1[[#All],[Name]])} -> Heat Illness Prevention - Supervisors
A13: 39465 | B13: Hearing Conservation | C13: FALSE | D13: hearing-conservation | E13: 1246989 | F13: {=_xlfn.XLOOKUP(salusCertTypes!A13,Table1[[#All],[salus id]],Table1[[#All],[Name]])} -> Hearing Conservation
... A45: 39498 | B45: Qualified Signal Person | C45: FALSE | D45: qualified-signal-person | E45: 1246989 | F45: {=_xlfn.XLOOKUP(salusCertTypes!A45,Table1[[#All],[salus id]],Table1[[#All],[Name]])} -> Qualified Signal Person
